shoten/__init__.py
shoten/cli.py
shoten/datatypes.py
shoten/filters.py
shoten/shoten.py
shoten-0.1.0.dist-info/AUTHORS.rst
shoten-0.1.0.dist-info/LICENSE
shoten-0.1.0.dist-info/METADATA
shoten-0.1.0.dist-info/WHEEL
shoten-0.1.0.dist-info/entry_points.txt
shoten-0.1.0.dist-info/top_level.txt
shoten-0.1.0.dist-info/RECORD
