Metadata-Version: 2.1
Name: shoten
Version: 0.1.0
Summary: ...
Home-page: https://github.com/adbar/shoten
Author: Adrien Barbaresi
Author-email: barbaresi@bbaw.de
License: GPLv3+
Keywords: nlp
Platform: UNKNOWN
Classifier: Development Status :: 2 - Pre-Alpha
Classifier: Intended Audience :: Developers
Classifier: Intended Audience :: Education
Classifier: Intended Audience :: Information Technology
Classifier: Intended Audience :: Science/Research
Classifier: License :: OSI Approved :: GNU General Public License v3 or later (GPLv3+)
Classifier: Programming Language :: Python :: 3
Classifier: Programming Language :: Python :: 3.6
Classifier: Programming Language :: Python :: 3.7
Classifier: Programming Language :: Python :: 3.8
Classifier: Programming Language :: Python :: 3.9
Classifier: Programming Language :: Python :: 3.10
Classifier: Topic :: Scientific/Engineering :: Information Analysis
Classifier: Topic :: Text Processing :: Linguistic
Requires-Python: >=3.6
Requires-Dist: courlan (>=0.6.0)
Requires-Dist: htmldate (>=1.2.0)
Requires-Dist: numpy
Requires-Dist: scikit-learn (>=0.24.2)
Requires-Dist: simplemma (>=0.5.0)
